puck/__init__.py
puck/backend.py
puck/cmd.py
puck/output.py
puck/parser.py
puck/test_backend.py
puck/test_cmd.py
puck/test_parser.py
puck-1.0.7.dist-info/DESCRIPTION.rst
puck-1.0.7.dist-info/METADATA
puck-1.0.7.dist-info/RECORD
puck-1.0.7.dist-info/WHEEL
puck-1.0.7.dist-info/entry_points.txt
puck-1.0.7.dist-info/metadata.json
puck-1.0.7.dist-info/top_level.txt
