Metadata-Version: 2.0
Name: puck
Version: 1.0.7
Summary: Python Update cheCKer
Home-page: https://github.com/NativeInstruments/puck
Author: Native Instruments GmbH
Author-email: cloud-devops+github@native-instruments.de
License: MIT
Platform: UNKNOWN
Classifier: License :: OSI Approved :: MIT License
Classifier: Programming Language :: Python :: 2.7
Classifier: Programming Language :: Python :: 3.6
Requires-Dist: click (==6.7)
Requires-Dist: six (==1.11.0)
Provides-Extra: test
Requires-Dist: pytest (==3.4.0); extra == 'test'
Requires-Dist: pytest-cov (==2.5.1); extra == 'test'
Requires-Dist: pytest-random (==0.02); extra == 'test'
Requires-Dist: mock (==2.0.0); extra == 'test'
